<?xml version="1.0" encoding="utf-8"?>
<!DOCTYPE hibernate-mapping PUBLIC "-//Hibernate/Hibernate Mapping DTD 3.0//EN"
"http://hibernate.sourceforge.net/hibernate-mapping-3.0.dtd">
<!-- 
    Mapping file autogenerated by MyEclipse Persistence Tools
-->
<hibernate-mapping>
    <class name="com.baosight.mode.TbGovInfoPubContent" table="TB_GOV_INFO_PUB_CONTENT" schema="SSOADMIN">
        <id name="fileId" type="java.lang.String">
            <column name="FILE_ID" length="32" />
            <generator class="uuid.hex" />
        </id>
        <property name="infoSource" type="java.lang.String">
            <column name="INFO_SOURCE" length="30" />
        </property>
        <property name="title" type="java.lang.String">
            <column name="TITLE" length="100" />
        </property>
        <property name="authorName" type="java.lang.String">
            <column name="AUTHOR_NAME" length="20" />
        </property>
        <property name="keyword" type="java.lang.String">
            <column name="KEYWORD" length="1000" />
        </property>
        <property name="summary" type="java.lang.String">
            <column name="SUMMARY" length="1000" />
        </property>
        <property name="content" type="java.sql.Clob">
            <column name="CONTENT" />
        </property>
        <property name="createTime" type="java.util.Date">
            <column name="CREATE_TIME" length="7" />
        </property>
        <property name="publishType" type="java.lang.String">
            <column name="PUBLISH_TYPE" length="10" />
        </property>
        <property name="fileCode" type="java.lang.String">
            <column name="FILE_CODE" length="50" />
        </property>
        <property name="infoSubject" type="java.lang.String">
            <column name="INFO_SUBJECT" length="32" />
        </property>
        <property name="offerWay" type="java.lang.String">
            <column name="OFFER_WAY" length="10" />
        </property>
        <property name="applyId" type="java.lang.String">
            <column name="APPLY_ID" length="40" />
        </property>
        <property name="status" type="java.lang.Long">
            <column name="STATUS" precision="22" scale="0" />
        </property>
        <property name="attr1" type="java.lang.String">
            <column name="ATTR1" length="200" />
        </property>
        <property name="attr2" type="java.lang.String">
            <column name="ATTR2" length="200" />
        </property>
        <property name="attr3" type="java.lang.String">
            <column name="ATTR3" length="200" />
        </property>
        <property name="sendTo" type="java.lang.Long">
            <column name="SEND_TO" precision="22" scale="0" />
        </property>
        <property name="lshType" type="java.lang.String">
            <column name="LSH_TYPE" length="2" />
        </property>
    </class>
</hibernate-mapping>
